Metadata-Version: 2.1
Name: django-fast-frontend
Version: 0.2.1
Summary: Turbocharge Front-End Creation with Django-Admin-Like Configuration
Home-page: https://github.com/MaxOnceProject/Django-Fast-Frontend
Author: Blogbeat
Author-email: support@blogbeat.app
Classifier: Programming Language :: Python :: 3
Classifier: License :: OSI Approved :: MIT License
Classifier: Operating System :: OS Independent
Classifier: Framework :: Django
Requires-Python: >=3.8
License-File: LICENSE
Requires-Dist: django >=4.0
Requires-Dist: django-bootstrap5 >=21.1
